jupyter_glances_proxy/__init__.py
jupyter_glances_proxy/glances.svg
jupyter_glances_proxy/jupyter_config.py
jupyter_glances_proxy-0.0.2.dist-info/METADATA
jupyter_glances_proxy-0.0.2.dist-info/WHEEL
jupyter_glances_proxy-0.0.2.dist-info/entry_points.txt
jupyter_glances_proxy-0.0.2.dist-info/licenses/LICENSE.md
jupyter_glances_proxy-0.0.2.dist-info/RECORD
