Metadata-Version: 2.1
Name: jupyter-glances-proxy
Version: 0.0.2
Summary: Jupyter server proxy for glances
Project-URL: Homepage, https://github.com/huntdatacenter/jupyter-glances-proxy
Author-email: Matus Kosut <matus.kosut@ntnu.no>, Diepiriye Okujagu <diepirio@ntnu.no>
License: MIT License
License-File: LICENSE.md
Keywords: Jupyter Proxy,Jupyter Server Proxy,JupyterLab
Classifier: Framework :: Jupyter
Classifier: Framework :: Jupyter :: JupyterLab
Classifier: Intended Audience :: Developers
Classifier: License :: OSI Approved :: MIT License
Classifier: Natural Language :: English
Classifier: Programming Language :: Python :: 3
Classifier: Programming Language :: Python :: 3.8
Classifier: Programming Language :: Python :: 3.9
Classifier: Programming Language :: Python :: 3.10
Requires-Python: >=3.8
Requires-Dist: glances[web]
Requires-Dist: jupyter-server-proxy>=3.2.2
Provides-Extra: dev
Requires-Dist: black; extra == 'dev'
Requires-Dist: pytest; extra == 'dev'
Requires-Dist: pytest-cov; extra == 'dev'
Requires-Dist: ruamel-yaml; extra == 'dev'
